pytest_jira_xfail/__init__.py
pytest_jira_xfail/annotations.py
pytest_jira_xfail/jira_helper.py
pytest_jira_xfail-1.2.1.dist-info/LICENSE
pytest_jira_xfail-1.2.1.dist-info/METADATA
pytest_jira_xfail-1.2.1.dist-info/WHEEL
pytest_jira_xfail-1.2.1.dist-info/top_level.txt
pytest_jira_xfail-1.2.1.dist-info/RECORD
