Metadata-Version: 2.1
Name: pytest-jira-xfail
Version: 1.2.1
Summary: Plugin skips (xfail) tests if unresolved Jira issue(s) linked
Home-page: https://github.com/JamalZeynalov/pytest-jira-xfail
Author: Jamal Zeinalov
Author-email: jamal.zeynalov@gmail.com
Classifier: Programming Language :: Python :: 3
Classifier: License :: OSI Approved :: MIT License
Classifier: Operating System :: OS Independent
Requires-Python: >=3.9
License-File: LICENSE
Requires-Dist: pytest >=7.2.0
Requires-Dist: requests >=2.28.1
Requires-Dist: setuptools >=65.5.1
Requires-Dist: jira >=3.4.1
Requires-Dist: singleton-decorator >=1.0.0
Requires-Dist: allure-pytest >=2.11.1
Requires-Dist: selenium >=4.6.0
Requires-Dist: pytest-playwright >=0.3.3
Requires-Dist: playwright >=1.43.0
